dns_crawler/__init__.py
dns_crawler/certificate.py
dns_crawler/config_loader.py
dns_crawler/controller.py
dns_crawler/crawl.py
dns_crawler/dns_utils.py
dns_crawler/geoip_utils.py
dns_crawler/hsts_utils.py
dns_crawler/ip_utils.py
dns_crawler/mail_utils.py
dns_crawler/redis_utils.py
dns_crawler/single.py
dns_crawler/timestamp.py
dns_crawler/utils.py
dns_crawler/web_utils.py
dns_crawler/worker.py
dns_crawler/workers.py
dns_crawler-1.6.5.dist-info/LICENSE
dns_crawler-1.6.5.dist-info/METADATA
dns_crawler-1.6.5.dist-info/WHEEL
dns_crawler-1.6.5.dist-info/entry_points.txt
dns_crawler-1.6.5.dist-info/top_level.txt
dns_crawler-1.6.5.dist-info/RECORD
