Metadata-Version: 2.1
Name: dns-crawler
Version: 1.6.5
Summary: A distributed crawler for getting info about DNS domains and services attached to them.
Author-email: Jiri Helebrant <jiri.helebrant@nic.cz>
License: GPL version 3
Project-URL: homepage, https://gitlab.nic.cz/adam/dns-crawler/
Project-URL: changelog, https://gitlab.nic.cz/adam/dns-crawler/-/blob/master/CHANGELOG.md
Keywords: crawler,dns,http,https,smtp,dnssec
Requires-Python: >=3.7
License-File: LICENSE
Requires-Dist: asn1crypto ==1.5.1
Requires-Dist: cert-human ==1.0.7
Requires-Dist: cryptography ==38.0.4
Requires-Dist: ecdsa ==0.18.0
Requires-Dist: forcediphttpsadapter ==1.0.2
Requires-Dist: geoip2 ==3.0.0
Requires-Dist: hstspreload
Requires-Dist: idna ==2.10
Requires-Dist: pyaml ==21.10.1
Requires-Dist: PyICU ==2.13.1
Requires-Dist: pyOpenSSL ==23.1.1
Requires-Dist: redis ==4.5.4
Requires-Dist: requests-toolbelt ==0.10.1
Requires-Dist: requests ==2.23.0
Requires-Dist: rq ==1.13.0
Requires-Dist: dnspython ==2.3.0
Requires-Dist: checkdmarc ==4.3.1
Requires-Dist: python-magic ==0.4.27
